odoo8_addon_project_sla-8.0.1.0.0.99.dev47-py3.8-nspkg.pth
odoo_addons/project_sla/__init__.py
odoo_addons/project_sla/__openerp__.py
odoo_addons/project_sla/analytic_account.py
odoo_addons/project_sla/analytic_account_view.xml
odoo_addons/project_sla/m2m.py
odoo_addons/project_sla/project_issue.py
odoo_addons/project_sla/project_issue_view.xml
odoo_addons/project_sla/project_sla.py
odoo_addons/project_sla/project_sla_control.py
odoo_addons/project_sla/project_sla_control_data.xml
odoo_addons/project_sla/project_sla_control_view.xml
odoo_addons/project_sla/project_sla_demo.xml
odoo_addons/project_sla/project_sla_view.xml
odoo_addons/project_sla/project_task.py
odoo_addons/project_sla/project_task_view.xml
odoo_addons/project_sla/project_view.xml
odoo_addons/project_sla/i18n/am.po
odoo_addons/project_sla/i18n/ar.po
odoo_addons/project_sla/i18n/bg.po
odoo_addons/project_sla/i18n/bs.po
odoo_addons/project_sla/i18n/ca.po
odoo_addons/project_sla/i18n/ca_ES.po
odoo_addons/project_sla/i18n/cs.po
odoo_addons/project_sla/i18n/da.po
odoo_addons/project_sla/i18n/da_DK.po
odoo_addons/project_sla/i18n/de.po
odoo_addons/project_sla/i18n/el.po
odoo_addons/project_sla/i18n/el_GR.po
odoo_addons/project_sla/i18n/en_GB.po
odoo_addons/project_sla/i18n/es.po
odoo_addons/project_sla/i18n/es_AR.po
odoo_addons/project_sla/i18n/es_CL.po
odoo_addons/project_sla/i18n/es_CO.po
odoo_addons/project_sla/i18n/es_CR.po
odoo_addons/project_sla/i18n/es_DO.po
odoo_addons/project_sla/i18n/es_EC.po
odoo_addons/project_sla/i18n/es_ES.po
odoo_addons/project_sla/i18n/es_MX.po
odoo_addons/project_sla/i18n/es_PE.po
odoo_addons/project_sla/i18n/es_PY.po
odoo_addons/project_sla/i18n/es_VE.po
odoo_addons/project_sla/i18n/et.po
odoo_addons/project_sla/i18n/fa.po
odoo_addons/project_sla/i18n/fi.po
odoo_addons/project_sla/i18n/fr.po
odoo_addons/project_sla/i18n/fr_CA.po
odoo_addons/project_sla/i18n/fr_CH.po
odoo_addons/project_sla/i18n/gl.po
odoo_addons/project_sla/i18n/gl_ES.po
odoo_addons/project_sla/i18n/he.po
odoo8_addon_project_sla-8.0.1.0.0.99.dev47.dist-info/METADATA
odoo8_addon_project_sla-8.0.1.0.0.99.dev47.dist-info/WHEEL
odoo8_addon_project_sla-8.0.1.0.0.99.dev47.dist-info/namespace_packages.txt
odoo8_addon_project_sla-8.0.1.0.0.99.dev47.dist-info/top_level.txt
odoo8_addon_project_sla-8.0.1.0.0.99.dev47.dist-info/RECORD
